README.md
setup.py
django_fandango.egg-info/PKG-INFO
django_fandango.egg-info/SOURCES.txt
django_fandango.egg-info/dependency_links.txt
django_fandango.egg-info/not-zip-safe
django_fandango.egg-info/requires.txt
django_fandango.egg-info/top_level.txt
fandango/__init__.py
fandango/admin.py
fandango/apps.py
fandango/backends.py
fandango/bootstrap.py
fandango/context_processors.py
fandango/middleware.py
fandango/settings.py
fandango/urls.py
fandango/boostrap/__init__.py
fandango/boostrap/html.py
fandango/conf/__init__.py
fandango/conf/settings.py
fandango/db/__init__.py
fandango/db/fields.py
fandango/db/models/__init__.py
fandango/db/models/base.py
fandango/db/models/django_log_entry.py
fandango/db/models/klass.py
fandango/db/models/log_level.py
fandango/db/models/logged_exception.py
fandango/db/models/profile.py
fandango/forms/__init__.py
fandango/forms/auth_forms.py
fandango/forms/base.py
fandango/forms/forms.py
fandango/migrations/0001_initial.py
fandango/migrations/__init__.py
fandango/templatetags/__init__.py
fandango/templatetags/bootstrap_tags.py
fandango/templatetags/fandango.py
fandango/utils/__init__.py
fandango/utils/db.py
fandango/utils/disk.py
fandango/utils/html.py
fandango/utils/humanize.py
fandango/utils/models.py
fandango/utils/strings.py
fandango/utils/utils.py
fandango/views/__init__.py
fandango/views/auth_views.py
fandango/views/base.py
fandango/views/json_views.py
fandango/views/views.py