Metadata-Version: 1.1
Name: django-fandango
Version: 0.0.1a0
Summary: Django additions and ...thingies...
Home-page: https://github.com/saturnus-ringar/django-fandango
Author: Saturnus Ringar
Author-email: stefan@gigguide.se
License: BSD
Download-URL: https://github.com/saturnus-ringar/django-fandango/tarball/0.0.1a0
Platform: UNKNOWN
